{
  "generatedAt": "2026-05-11T15:39:12.291Z",
  "gitCommit": "90d1d447bd2e10b1a737ada2c08ae5f9602ef165",
  "gitBranch": "main",
  "version": "0.1.0",
  "testSuite": {
    "passed": 372,
    "total": 372,
    "files": 15
  },
  "auditChecks": {
    "passed": 13,
    "total": 13
  },
  "invariants": {
    "total": 12,
    "allCovered": true
  },
  "validators": {
    "demo:web:validate": {
      "passed": true,
      "assertions": 106
    },
    "demo:support:validate": {
      "passed": true,
      "assertions": 13
    },
    "review:validate": {
      "passed": true,
      "assertions": 110
    }
  },
  "manifestChecksum": "d9926fc908202cfc1cecfa48d73b43c3826797ee86603b041af825806db2815d"
}
